Classfile /home/user1/workspace/java-demo/spring-demo/spring-bean-demo/target/classes/huaminglin/demo/spring/bean/SpringBeanDemo.class
  Last modified Jun 28, 2018; size 2546 bytes
  MD5 checksum 46cc1cdbcad15bba17a8249c1cdcf604
  Compiled from "SpringBeanDemo.java"
public class huaminglin.demo.spring.bean.SpringBeanDemo
  minor version: 0
  major version: 52
  flags: ACC_PUBLIC, ACC_SUPER
Constant pool:
    #1 = Methodref          #31.#66       // java/lang/Object."<init>":()V
    #2 = Class              #67           // huaminglin/demo/spring/bean/SpringBeanDemo$MyConfiguration
    #3 = String             #44           // myDate2
    #4 = Class              #68           // java/lang/Class
    #5 = Class              #69           // java/lang/String
    #6 = Methodref          #4.#70        // java/lang/Class.getDeclaredMethod:(Ljava/lang/String;[Ljava/lang/Class;)Ljava/lang/reflect/Method;
    #7 = Class              #71           // java/lang/NoSuchMethodException
    #8 = Methodref          #7.#72        // java/lang/NoSuchMethodException.printStackTrace:()V
    #9 = Methodref          #73.#74       // java/lang/reflect/Method.getParameters:()[Ljava/lang/reflect/Parameter;
   #10 = Fieldref           #75.#76       // java/lang/System.out:Ljava/io/PrintStream;
   #11 = Class              #77           // java/lang/StringBuilder
   #12 = Methodref          #11.#66       // java/lang/StringBuilder."<init>":()V
   #13 = String             #78           // detectParameterNameByReflect:
   #14 = Methodref          #11.#79       // java/lang/StringBuilder.append:(Ljava/lang/String;)Ljava/lang/StringBuilder;
   #15 = Methodref          #80.#81       // java/lang/reflect/Parameter.getName:()Ljava/lang/String;
   #16 = Methodref          #11.#82       // java/lang/StringBuilder.toString:()Ljava/lang/String;
   #17 = Methodref          #83.#84       // java/io/PrintStream.println:(Ljava/lang/String;)V
   #18 = Class              #85           // org/springframework/core/DefaultParameterNameDiscoverer
   #19 = Methodref          #18.#66       // org/springframework/core/DefaultParameterNameDiscoverer."<init>":()V
   #20 = Methodref          #18.#86       // org/springframework/core/DefaultParameterNameDiscoverer.getParameterNames:(Ljava/lang/reflect/Method;)[Ljava/lang/String;
   #21 = String             #87           // detectParameterNameBySpring:
   #22 = String             #88           // detectParameterNameBySpring failed
   #23 = Methodref          #30.#89       // huaminglin/demo/spring/bean/SpringBeanDemo.detectParameterNameByReflect:()V
   #24 = Methodref          #30.#90       // huaminglin/demo/spring/bean/SpringBeanDemo.detectParameterNameBySpring:()V
   #25 = Class              #91           // org/springframework/context/annotation/AnnotationConfigApplicationContext
   #26 = Methodref          #25.#66       // org/springframework/context/annotation/AnnotationConfigApplicationContext."<init>":()V
   #27 = String             #92           // huaminglin.demo.spring.bean
   #28 = Methodref          #25.#93       // org/springframework/context/annotation/AnnotationConfigApplicationContext.scan:([Ljava/lang/String;)V
   #29 = Methodref          #25.#94       // org/springframework/context/annotation/AnnotationConfigApplicationContext.refresh:()V
   #30 = Class              #95           // huaminglin/demo/spring/bean/SpringBeanDemo
   #31 = Class              #96           // java/lang/Object
   #32 = Utf8               MyConfiguration
   #33 = Utf8               InnerClasses
   #34 = Utf8               <init>
   #35 = Utf8               ()V
   #36 = Utf8               Code
   #37 = Utf8               LineNumberTable
   #38 = Utf8               LocalVariableTable
   #39 = Utf8               this
   #40 = Utf8               Lhuaminglin/demo/spring/bean/SpringBeanDemo;
   #41 = Utf8               detectParameterNameByReflect
   #42 = Utf8               e
   #43 = Utf8               Ljava/lang/NoSuchMethodException;
   #44 = Utf8               myDate2
   #45 = Utf8               Ljava/lang/reflect/Method;
   #46 = Utf8               parameter
   #47 = Utf8               Ljava/lang/reflect/Parameter;
   #48 = Utf8               StackMapTable
   #49 = Class              #97           // java/lang/reflect/Method
   #50 = Class              #71           // java/lang/NoSuchMethodException
   #51 = Utf8               detectParameterNameBySpring
   #52 = Utf8               discoverer
   #53 = Utf8               Lorg/springframework/core/DefaultParameterNameDiscoverer;
   #54 = Utf8               parameterNames
   #55 = Utf8               [Ljava/lang/String;
   #56 = Class              #85           // org/springframework/core/DefaultParameterNameDiscoverer
   #57 = Class              #55           // "[Ljava/lang/String;"
   #58 = Utf8               main
   #59 = Utf8               ([Ljava/lang/String;)V
   #60 = Utf8               args
   #61 = Utf8               context
   #62 = Utf8               Lorg/springframework/context/annotation/AnnotationConfigApplicationContext;
   #63 = Utf8               MethodParameters
   #64 = Utf8               SourceFile
   #65 = Utf8               SpringBeanDemo.java
   #66 = NameAndType        #34:#35       // "<init>":()V
   #67 = Utf8               huaminglin/demo/spring/bean/SpringBeanDemo$MyConfiguration
   #68 = Utf8               java/lang/Class
   #69 = Utf8               java/lang/String
   #70 = NameAndType        #98:#99       // getDeclaredMethod:(Ljava/lang/String;[Ljava/lang/Class;)Ljava/lang/reflect/Method;
   #71 = Utf8               java/lang/NoSuchMethodException
   #72 = NameAndType        #100:#35      // printStackTrace:()V
   #73 = Class              #97           // java/lang/reflect/Method
   #74 = NameAndType        #101:#102     // getParameters:()[Ljava/lang/reflect/Parameter;
   #75 = Class              #103          // java/lang/System
   #76 = NameAndType        #104:#105     // out:Ljava/io/PrintStream;
   #77 = Utf8               java/lang/StringBuilder
   #78 = Utf8               detectParameterNameByReflect:
   #79 = NameAndType        #106:#107     // append:(Ljava/lang/String;)Ljava/lang/StringBuilder;
   #80 = Class              #108          // java/lang/reflect/Parameter
   #81 = NameAndType        #109:#110     // getName:()Ljava/lang/String;
   #82 = NameAndType        #111:#110     // toString:()Ljava/lang/String;
   #83 = Class              #112          // java/io/PrintStream
   #84 = NameAndType        #113:#114     // println:(Ljava/lang/String;)V
   #85 = Utf8               org/springframework/core/DefaultParameterNameDiscoverer
   #86 = NameAndType        #115:#116     // getParameterNames:(Ljava/lang/reflect/Method;)[Ljava/lang/String;
   #87 = Utf8               detectParameterNameBySpring:
   #88 = Utf8               detectParameterNameBySpring failed
   #89 = NameAndType        #41:#35       // detectParameterNameByReflect:()V
   #90 = NameAndType        #51:#35       // detectParameterNameBySpring:()V
   #91 = Utf8               org/springframework/context/annotation/AnnotationConfigApplicationContext
   #92 = Utf8               huaminglin.demo.spring.bean
   #93 = NameAndType        #117:#59      // scan:([Ljava/lang/String;)V
   #94 = NameAndType        #118:#35      // refresh:()V
   #95 = Utf8               huaminglin/demo/spring/bean/SpringBeanDemo
   #96 = Utf8               java/lang/Object
   #97 = Utf8               java/lang/reflect/Method
   #98 = Utf8               getDeclaredMethod
   #99 = Utf8               (Ljava/lang/String;[Ljava/lang/Class;)Ljava/lang/reflect/Method;
  #100 = Utf8               printStackTrace
  #101 = Utf8               getParameters
  #102 = Utf8               ()[Ljava/lang/reflect/Parameter;
  #103 = Utf8               java/lang/System
  #104 = Utf8               out
  #105 = Utf8               Ljava/io/PrintStream;
  #106 = Utf8               append
  #107 = Utf8               (Ljava/lang/String;)Ljava/lang/StringBuilder;
  #108 = Utf8               java/lang/reflect/Parameter
  #109 = Utf8               getName
  #110 = Utf8               ()Ljava/lang/String;
  #111 = Utf8               toString
  #112 = Utf8               java/io/PrintStream
  #113 = Utf8               println
  #114 = Utf8               (Ljava/lang/String;)V
  #115 = Utf8               getParameterNames
  #116 = Utf8               (Ljava/lang/reflect/Method;)[Ljava/lang/String;
  #117 = Utf8               scan
  #118 = Utf8               refresh
{
  public huaminglin.demo.spring.bean.SpringBeanDemo();
    descriptor: ()V
    flags: ACC_PUBLIC
    Code:
      stack=1, locals=1, args_size=1
         0: aload_0
         1: invokespecial #1                  // Method java/lang/Object."<init>":()V
         4: return
      LineNumberTable:
        line 12: 0
      LocalVariableTable:
        Start  Length  Slot  Name   Signature
            0       5     0  this   Lhuaminglin/demo/spring/bean/SpringBeanDemo;

  public static void main(java.lang.String[]);
    descriptor: ([Ljava/lang/String;)V
    flags: ACC_PUBLIC, ACC_STATIC
    Code:
      stack=5, locals=2, args_size=1
         0: invokestatic  #23                 // Method detectParameterNameByReflect:()V
         3: invokestatic  #24                 // Method detectParameterNameBySpring:()V
         6: new           #25                 // class org/springframework/context/annotation/AnnotationConfigApplicationContext
         9: dup
        10: invokespecial #26                 // Method org/springframework/context/annotation/AnnotationConfigApplicationContext."<init>":()V
        13: astore_1
        14: aload_1
        15: iconst_1
        16: anewarray     #5                  // class java/lang/String
        19: dup
        20: iconst_0
        21: ldc           #27                 // String huaminglin.demo.spring.bean
        23: aastore
        24: invokevirtual #28                 // Method org/springframework/context/annotation/AnnotationConfigApplicationContext.scan:([Ljava/lang/String;)V
        27: aload_1
        28: invokevirtual #29                 // Method org/springframework/context/annotation/AnnotationConfigApplicationContext.refresh:()V
        31: return
      LineNumberTable:
        line 68: 0
        line 69: 3
        line 70: 6
        line 71: 14
        line 72: 27
        line 73: 31
      LocalVariableTable:
        Start  Length  Slot  Name   Signature
            0      32     0  args   [Ljava/lang/String;
           14      18     1 context   Lorg/springframework/context/annotation/AnnotationConfigApplicationContext;
    MethodParameters:
      Name                           Flags
      args
}
SourceFile: "SpringBeanDemo.java"
InnerClasses:
     public static #32= #2 of #30; //MyConfiguration=class huaminglin/demo/spring/bean/SpringBeanDemo$MyConfiguration of class huaminglin/demo/spring/bean/SpringBeanDemo
